[
    {
        "make": "NISSAN",
        "model": "LEAF",
        "transmission": "AUTOMATIC",
        "car_group": "1ELE",
        "supplier": "ALAMO",
        "total_price": 304.33,
        "price_per_day": 60.87,
        "pickup_datetime": "2024-11-16T10:00:00.000",
        "dropoff_datetime": "2024-11-21T10:00:00.000",
        "rental_period": 5,
        "source": "do_you_spain",
        "day": 16,
        "month": 10,
        "year": 2024,
        "hour": 12
    },
    {
        "make": "NISSAN",
        "model": "LEAF",
        "transmission": "AUTOMATIC",
        "car_group": "1ELE",
        "supplier": "ALAMO",
        "total_price": 1278.41,
        "price_per_day": 60.88,
        "pickup_datetime": "2024-11-16T10:00:00.000",
        "dropoff_datetime": "2024-12-07T10:00:00.000",
        "rental_period": 21,
        "source": "do_you_spain",
        "day": 16,
        "month": 10,
        "year": 2024,
        "hour": 12
    },
    {
        "make": "NISSAN",
        "model": "LEAF",
        "transmission": "AUTOMATIC",
        "car_group": "1ELE",
        "supplier": "ALAMO",
        "total_price": 608.9,
        "price_per_day": 60.89,
        "pickup_datetime": "2024-11-16T10:00:00.000",
        "dropoff_datetime": "2024-11-26T10:00:00.000",
        "rental_period": 10,
        "source": "do_you_spain",
        "day": 16,
        "month": 10,
        "year": 2024,
        "hour": 12
    },
    {
        "make": "BMW",
        "model": "3 SERIES",
        "transmission": "AUTOMATIC",
        "car_group": "2A",
        "supplier": "DRIVALIA",
        "total_price": 224.78,
        "price_per_day": 32.11,
        "pickup_datetime": "2024-11-16T10:00:00.000",
        "dropoff_datetime": "2024-11-23T10:00:00.000",
        "rental_period": 7,
        "source": "do_you_spain",
        "day": 16,
        "month": 10,
        "year": 2024,
        "hour": 12
    },
    {
        "make": "NISSAN",
        "model": "LEAF",
        "transmission": "AUTOMATIC",
        "car_group": "1ELE",
        "supplier": "ALAMO",
        "total_price": 304.33,
        "price_per_day": 60.87,
        "pickup_datetime": "2024-11-16T10:00:00.000",
        "dropoff_datetime": "2024-11-21T10:00:00.000",
        "rental_period": 5,
        "source": "do_you_spain",
        "day": 16,
        "month": 10,
        "year": 2024,
        "hour": 12
    },
    {
        "make": "NISSAN",
        "model": "QASHQAI",
        "transmission": "MANUAL",
        "car_group": "1ELE",
        "supplier": "ALAMO",
        "total_price": 1278.41,
        "price_per_day": 60.88,
        "pickup_datetime": "2024-10-20T10:00:00.000",
        "dropoff_datetime": "2024-10-23T10:00:00.000",
        "rental_period": 3,
        "source": "do_you_spain",
        "day": 20,
        "month": 10,
        "year": 2024,
        "hour": 10
    },
    {
        "make": "FORD",
        "model": "FOCUS",
        "transmission": "AUTOMATIC",
        "car_group": "1A",
        "supplier": "HERTZ",
        "total_price": 608.90,
        "price_per_day": 60.89,
        "pickup_datetime": "2024-10-20T10:00:00.000",
        "dropoff_datetime": "2024-10-23T10:00:00.000",
        "rental_period": 3,
        "source": "do_you_spain",
        "day": 20,
        "month": 10,
        "year": 2024,
        "hour": 10
    },
    {
        "make": "BMW",
        "model": "X1",
        "transmission": "AUTOMATIC",
        "car_group": "2A",
        "supplier": "DRIVALIA",
        "total_price": 224.78,
        "price_per_day": 32.11,
        "pickup_datetime": "2024-10-20T10:00:00.000",
        "dropoff_datetime": "2024-10-23T10:00:00.000",
        "rental_period": 3,
        "source": "do_you_spain",
        "day": 20,
        "month": 10,
        "year": 2024,
        "hour": 10
    },
    {
        "make": "RENAULT",
        "model": "CAPTUR",
        "transmission": "AUTOMATIC",
        "car_group": "1ELE",
        "supplier": "ALAMO",
        "total_price": 304.33,
        "price_per_day": 60.87,
        "pickup_datetime": "2024-10-20T10:00:00.000",
        "dropoff_datetime": "2024-10-23T10:00:00.000",
        "rental_period": 3,
        "source": "do_you_spain",
        "day": 20,
        "month": 10,
        "year": 2024,
        "hour": 10
    },
    {
        "make": "MERCEDES",
        "model": "A CLASS",
        "transmission": "AUTOMATIC",
        "car_group": "2A",
        "supplier": "EUROPCAR",
        "total_price": 1278.41,
        "price_per_day": 60.88,
        "pickup_datetime": "2024-10-20T10:00:00.000",
        "dropoff_datetime": "2024-10-23T10:00:00.000",
        "rental_period": 3,
        "source": "do_you_spain",
        "day": 20,
        "month": 10,
        "year": 2024,
        "hour": 10
    },
    {
        "make": "TOYOTA",
        "model": "YARIS",
        "transmission": "MANUAL",
        "car_group": "1A",
        "supplier": "ALAMO",
        "total_price": 608.90,
        "price_per_day": 60.89,
        "pickup_datetime": "2024-10-20T10:00:00.000",
        "dropoff_datetime": "2024-10-23T10:00:00.000",
        "rental_period": 3,
        "source": "do_you_spain",
        "day": 20,
        "month": 10,
        "year": 2024,
        "hour": 10
    },
    {
        "make": "VOLKSWAGEN",
        "model": "GOLF",
        "transmission": "AUTOMATIC",
        "car_group": "2A",
        "supplier": "DRIVALIA",
        "total_price": 224.78,
        "price_per_day": 32.11,
        "pickup_datetime": "2024-10-20T10:00:00.000",
        "dropoff_datetime": "2024-10-23T10:00:00.000",
        "rental_period": 3,
        "source": "do_you_spain",
        "day": 20,
        "month": 10,
        "year": 2024,
        "hour": 10
    }
]